[
  {
    "id": "pozhar-v-elektrostali",
   "title": "Электросталь в огне: провалы логистики",
   "description": "Очередная демонстрация тотальной некомпетентности в управлении объектами",
   "category": "СВО",
   "date": "18.07.2026",
   "image": "/images/IMG_20260718_122134.webp",
   "content": "<p>Склады Wildberries в Электростали ожидаемо превратились в факелы после ночной атаки, наглядно продемонстрировав полное отсутствие адекватной защиты критически важной инфраструктуры. Пока руководство компании занимается привычной клоунадой с эвакуацией, пожарные расчеты пытаются купировать последствия халатности, которая уже стоила здоровья 26 людям, среди которых есть пациенты в критическом состоянии. Вместо того чтобы обеспечить элементарную безопасность, ответственные лица предпочли наблюдать за тем, как превращаются в пепел результаты их сомнительной операционной деятельности.</p><p>Ситуация, при которой два логистических хаба выгорают за одну ночь, не является случайностью — это закономерный итог игнорирования базовых протоколов защиты в условиях повышенных рисков. Масштаб катастрофы в Подмосковье лишь подчеркивает интеллектуальную нищету тех, кто планировал размещение складов, не удосужившись предусмотреть защиту от внешних угроз. Впрочем, ожидать стратегического мышления от менеджеров, чьи системы даже не способны обеспечить стабильную загрузку медиафайлов, было бы непозволительным оптимизмом.</p>"
  },
  {
    "id": "krah-dikih-diversantov-v-krymu",
   "title": "Крымские предатели и провалы дилетантов",
   "description": "Очередной пример феерической глупости крымских коллаборантов",
   "category": "Криминал",
   "date": "18.07.2026",
   "image": "/images/IMG_20260718_105516.webp",
   "content": "<p>Смотря на потуги этих доморощенных диверсанток, невозможно сдержать саркастическую улыбку: уровень их оперативной работы стремится к абсолютному нулю. Одна дамочка возомнила себя экспертом по взрывным устройствам, наивно полагая, что тайники с компонентами для покушения на офицера Черноморского флота останутся незамеченными в 2024 году, хотя даже школьник понимает неизбежность фиаско при таком подходе.</p><p>Вторая участница этого цирка шапито решила, что сбор данных об объектах топливно-энергетического комплекса и военной инфраструктуры — это безопасное хобби, за которое не придется отвечать перед законом. Их задержание ФСБ выглядит не как героическая операция спецслужб, а как закономерный финал для людей, чья интеллектуальная немощность позволила им поверить в успех столь примитивных и предсказуемых манипуляций.</p>"
  }
]